nacos_py_client/__init__.py
nacos_py_client/_chooser.py
nacos_py_client/cache.py
nacos_py_client/client.py
nacos_py_client/endpoints/__init__.py
nacos_py_client/endpoints/config.py
nacos_py_client/endpoints/endpoint.py
nacos_py_client/endpoints/instance.py
nacos_py_client/endpoints/namespace.py
nacos_py_client/endpoints/service.py
nacos_py_client/exception.py
nacos_py_client/helper.py
nacos_py_client/serializer.py
nacos_py_client/typings.py
nacos_py_client-0.2.6.dist-info/METADATA
nacos_py_client-0.2.6.dist-info/WHEEL
nacos_py_client-0.2.6.dist-info/RECORD
